<Namespace Name="System.Drawing.Text">
  <Metadata><Meta Name="ms.openlocfilehash" Value="fd826221ab994035d3f9d9463399d21510e12fc9" /><Meta Name="ms.sourcegitcommit" Value="9506e50ec7beb4fa30206b9840dc546b035a6600" /><Meta Name="ms.translationtype" Value="MT" /><Meta Name="ms.contentlocale" Value="de-DE" /><Meta Name="ms.lasthandoff" Value="07/23/2020" /><Meta Name="ms.locfileid" Value="83941438" /></Metadata><Docs>
    <summary>Der <see cref="N:System.Drawing.Text" />-Namespace stellt erweiterte GDI+-Typografiefunktionen bereit.</summary>
    <remarks>
      <format type="text/markdown"><![CDATA[  
  
## Remarks  
 Grundlegende Grafikfunktionen werden vom <xref:System.Drawing>-Namespace bereitgestellt. Mit den Klassen in diesem Namespace können Benutzer Auflistungen von Schriftarten erstellen und verwenden.  
  
> [!CAUTION]
>  Klassen im- <xref:System.Drawing.Text> Namespace werden nicht für die Verwendung in einem Windows-oder ASP.net-Dienst unterstützt. Der Versuch, diese Klassen innerhalb eines dieser Anwendungs Typen zu verwenden, kann zu unerwarteten Problemen führen, wie z. b. verminderter Dienstleistung und Lauf Zeit Ausnahmen.  
  
 ]]></format>
    </remarks>
    <related type="Article" href="/dotnet/framework/winforms/advanced/using-fonts-and-text">Verwenden von Schriftarten und Text</related>
  </Docs>
</Namespace>