<Namespace Name="System.Data.SqlTypes">
  <Metadata><Meta Name="ms.openlocfilehash" Value="62610ed1ebdc0a78ee71a3b3aded0ee3ac35786c" /><Meta Name="ms.sourcegitcommit" Value="11d168140aa8fade0768c2a9dde3e3bcacfdfb7d" /><Meta Name="ms.translationtype" Value="MT" /><Meta Name="ms.contentlocale" Value="de-DE" /><Meta Name="ms.lasthandoff" Value="05/27/2020" /><Meta Name="ms.locfileid" Value="83929064" /></Metadata><Docs>
    <summary><span data-ttu-id="65a83-101">Der <see cref="N:System.Data.SqlTypes" />-Namespace stellt Klassen für systemeigene Datentypen in SQL Server bereit.</span><span class="sxs-lookup"><span data-stu-id="65a83-101">The <see cref="N:System.Data.SqlTypes" /> namespace provides classes for native data types in SQL Server.</span></span> <span data-ttu-id="65a83-102">Diese Klassen stellen eine sicherere, schnellere Alternative zu Datentypen bereit, die von der Common Language Runtime (CLR) von .NET Framework bereitgestellt werden.</span><span class="sxs-lookup"><span data-stu-id="65a83-102">These classes provide a safer, faster alternative to the data types provided by the .NET Framework common language runtime (CLR).</span></span> <span data-ttu-id="65a83-103">Durch das Verwenden der Klassen in diesem Namespace können durch Verlust an Genauigkeit verursachte Typkonvertierungsfehler besser verhindert werden.</span><span class="sxs-lookup"><span data-stu-id="65a83-103">Using the classes in this namespace helps prevent type conversion errors caused by loss of precision.</span></span> <span data-ttu-id="65a83-104">Da andere Datentypen im Hintergrund in und aus **SqlTypes** konvertiert werden, führt das explizite Erstellen und Verwenden von Objekten in diesem Namespace auch zu einem schnelleren Code.</span><span class="sxs-lookup"><span data-stu-id="65a83-104">Because other data types are converted to and from **SqlTypes** behind the scenes, explicitly creating and using objects within this namespace also yields faster code.</span></span></summary>
    <remarks>
      <format type="text/markdown"><![CDATA[  
  
## Remarks  
 <span data-ttu-id="65a83-105">Jeder Datentyp in **SqlTypes** hat seinen äquivalenten Datentyp in SQL Server mit derselben zugrunde liegenden Datendarstellung.</span><span class="sxs-lookup"><span data-stu-id="65a83-105">Each data type in **SqlTypes** has its equivalent data type in SQL Server, with the same underlying data representation.</span></span> <span data-ttu-id="65a83-106">Viele davon verfügen auch über äquivalente Datentypen in der CLR.</span><span class="sxs-lookup"><span data-stu-id="65a83-106">Many of them also have equivalent data types in the CLR.</span></span> <span data-ttu-id="65a83-107">**SqlDateTime**, **SqlDecimal**und **SqlString** weisen jedoch unterschiedliche zugrunde liegende Datenstrukturen mit den entsprechenden .NET Framework-Datentypen auf.</span><span class="sxs-lookup"><span data-stu-id="65a83-107">However, **SqlDateTime**, **SqlDecimal**, and **SqlString** have different underlying data structures with their corresponding .NET Framework data types.</span></span>  
  
 <span data-ttu-id="65a83-108">In der folgenden Tabelle werden die Elemente des **SqlTypes** -Namespace Microsoft SQL Server-Datentypen und den Membern der <xref:System.Data.SqlDbType>-Enumeration zugeordnet.</span><span class="sxs-lookup"><span data-stu-id="65a83-108">The following table maps the members of the **SqlTypes** namespace to Microsoft SQL Server data types and to the members of the <xref:System.Data.SqlDbType> enumeration.</span></span>  
  
|<span data-ttu-id="65a83-109">.NET Framework SqlTypes</span><span class="sxs-lookup"><span data-stu-id="65a83-109">.NET Framework SqlTypes</span></span>|<span data-ttu-id="65a83-110">Native SQL Server</span><span class="sxs-lookup"><span data-stu-id="65a83-110">Native SQL Server</span></span>|<span data-ttu-id="65a83-111">.NET Framework SqlDbType</span><span class="sxs-lookup"><span data-stu-id="65a83-111">.NET Framework SqlDbType</span></span>|  
|-----------------------------|------------------------------------------------------------------------|------------------------------|  
|<xref:System.Data.SqlTypes.SqlBinary>|<span data-ttu-id="65a83-112">Binary, Image, timestamp, varbinary</span><span class="sxs-lookup"><span data-stu-id="65a83-112">binary, image, timestamp, varbinary</span></span>|<span data-ttu-id="65a83-113">Binary, Image, timestamp, varbinary</span><span class="sxs-lookup"><span data-stu-id="65a83-113">Binary, Image, TimeStamp, VarBinary</span></span>|  
|<xref:System.Data.SqlTypes.SqlBoolean>|<span data-ttu-id="65a83-114">bit</span><span class="sxs-lookup"><span data-stu-id="65a83-114">bit</span></span>|<span data-ttu-id="65a83-115">bit</span><span class="sxs-lookup"><span data-stu-id="65a83-115">Bit</span></span>|  
|<xref:System.Data.SqlTypes.SqlByte>|<span data-ttu-id="65a83-116">TINYINT</span><span class="sxs-lookup"><span data-stu-id="65a83-116">tinyint</span></span>|<span data-ttu-id="65a83-117">TinyInt</span><span class="sxs-lookup"><span data-stu-id="65a83-117">TinyInt</span></span>|  
|<xref:System.Data.SqlTypes.SqlBytes>|<span data-ttu-id="65a83-118">Binary, Image, timestamp, varbinary</span><span class="sxs-lookup"><span data-stu-id="65a83-118">binary, image, timestamp, varbinary</span></span>|<span data-ttu-id="65a83-119">Binary, Image, timestamp, varbinary</span><span class="sxs-lookup"><span data-stu-id="65a83-119">Binary, Image, TimeStamp, VarBinary</span></span>|  
|<xref:System.Data.SqlTypes.SqlChars>|<span data-ttu-id="65a83-120">Char, nchar, Text, ntext, nvarchar, varchar</span><span class="sxs-lookup"><span data-stu-id="65a83-120">char, nchar, text, ntext, nvarchar, varchar</span></span>|<span data-ttu-id="65a83-121">Char, NChar, Text, Ntext, NVarChar, VarChar</span><span class="sxs-lookup"><span data-stu-id="65a83-121">Char, NChar, Text, Ntext, NVarChar, VarChar</span></span>|  
|<xref:System.Data.SqlTypes.SqlDateTime>|<span data-ttu-id="65a83-122">datetime, smalldatetime</span><span class="sxs-lookup"><span data-stu-id="65a83-122">datetime, smalldatetime</span></span>|<span data-ttu-id="65a83-123">DateTime, smalldatetime</span><span class="sxs-lookup"><span data-stu-id="65a83-123">DateTime, SmallDateTime</span></span>|  
|<xref:System.Data.SqlTypes.SqlDecimal>|<span data-ttu-id="65a83-124">numerisch, dezimal</span><span class="sxs-lookup"><span data-stu-id="65a83-124">numeric, decimal</span></span>|<span data-ttu-id="65a83-125">Decimal</span><span class="sxs-lookup"><span data-stu-id="65a83-125">Decimal</span></span>|  
|<xref:System.Data.SqlTypes.SqlDouble>|<span data-ttu-id="65a83-126">float</span><span class="sxs-lookup"><span data-stu-id="65a83-126">float</span></span>|<span data-ttu-id="65a83-127">Float</span><span class="sxs-lookup"><span data-stu-id="65a83-127">Float</span></span>|  
|<xref:System.Data.SqlTypes.SqlFileStream>|<span data-ttu-id="65a83-128">varbinary</span><span class="sxs-lookup"><span data-stu-id="65a83-128">varbinary</span></span>|<span data-ttu-id="65a83-129">VarBinary</span><span class="sxs-lookup"><span data-stu-id="65a83-129">VarBinary</span></span>|  
|<xref:System.Data.SqlTypes.SqlGuid>|<span data-ttu-id="65a83-130">UNIQUEIDENTIFIER</span><span class="sxs-lookup"><span data-stu-id="65a83-130">uniqueidentifier</span></span>|<span data-ttu-id="65a83-131">UniqueIdentifier</span><span class="sxs-lookup"><span data-stu-id="65a83-131">UniqueIdentifier</span></span>|  
|<xref:System.Data.SqlTypes.SqlInt16>|<span data-ttu-id="65a83-132">SMALLINT</span><span class="sxs-lookup"><span data-stu-id="65a83-132">smallint</span></span>|<span data-ttu-id="65a83-133">SmallInt</span><span class="sxs-lookup"><span data-stu-id="65a83-133">SmallInt</span></span>|  
|<xref:System.Data.SqlTypes.SqlInt32>|<span data-ttu-id="65a83-134">INT</span><span class="sxs-lookup"><span data-stu-id="65a83-134">int</span></span>|<span data-ttu-id="65a83-135">Int</span><span class="sxs-lookup"><span data-stu-id="65a83-135">Int</span></span>|  
|<xref:System.Data.SqlTypes.SqlInt64>|<span data-ttu-id="65a83-136">BIGINT</span><span class="sxs-lookup"><span data-stu-id="65a83-136">bigint</span></span>|<span data-ttu-id="65a83-137">BigInt</span><span class="sxs-lookup"><span data-stu-id="65a83-137">BigInt</span></span>|  
|<xref:System.Data.SqlTypes.SqlMoney>|<span data-ttu-id="65a83-138">money, smallmoney.</span><span class="sxs-lookup"><span data-stu-id="65a83-138">money, smallmoney</span></span>|<span data-ttu-id="65a83-139">Money, smallmoney</span><span class="sxs-lookup"><span data-stu-id="65a83-139">Money, SmallMoney</span></span>|  
|<xref:System.Data.SqlTypes.SqlSingle>|<span data-ttu-id="65a83-140">real</span><span class="sxs-lookup"><span data-stu-id="65a83-140">real</span></span>|<span data-ttu-id="65a83-141">Real</span><span class="sxs-lookup"><span data-stu-id="65a83-141">Real</span></span>|  
|<xref:System.Data.SqlTypes.SqlString>|<span data-ttu-id="65a83-142">Char, nchar, Text, ntext, nvarchar, varchar</span><span class="sxs-lookup"><span data-stu-id="65a83-142">char, nchar, text, ntext, nvarchar, varchar</span></span>|<span data-ttu-id="65a83-143">Char, NChar, Text, Ntext, NVarChar, VarChar</span><span class="sxs-lookup"><span data-stu-id="65a83-143">Char, NChar, Text, Ntext, NVarChar, VarChar</span></span>|  
|<xref:System.Data.SqlTypes.SqlXml>|<span data-ttu-id="65a83-144">Xml</span><span class="sxs-lookup"><span data-stu-id="65a83-144">xml</span></span>|<span data-ttu-id="65a83-145">Xml</span><span class="sxs-lookup"><span data-stu-id="65a83-145">Xml</span></span>|  
  
 ]]></format>
    </remarks>
    <related type="Article" href="/dotnet/framework/data/adonet/sql-server-data-type-mappings"><span data-ttu-id="65a83-146">SQL Server-Datentypzuordnungen (ADO.NET)</span><span class="sxs-lookup"><span data-stu-id="65a83-146">SQL Server Data Type Mappings (ADO.NET)</span></span></related>
    <related type="Article" href="/dotnet/framework/data/adonet/sql/sql-server-data-types"><span data-ttu-id="65a83-147">SQL Server-Datentypen und ADO.NET</span><span class="sxs-lookup"><span data-stu-id="65a83-147">SQL Server Data Types and ADO.NET</span></span></related>
  </Docs>
</Namespace>