<Namespace Name="System.Collections.Specialized">
  <Metadata><Meta Name="ms.openlocfilehash" Value="637696c1cfaf33787fb6cb2b1cc593880aa0e8b3" /><Meta Name="ms.sourcegitcommit" Value="88014e1c5440e3df4f66ef04393854d15b1fd534" /><Meta Name="ms.translationtype" Value="MT" /><Meta Name="ms.contentlocale" Value="de-DE" /><Meta Name="ms.lasthandoff" Value="09/05/2019" /><Meta Name="ms.locfileid" Value="70522871" /></Metadata><Docs>
    <summary>Der <see cref="N:System.Collections.Specialized" />-Namespace enthält besondere und stark typisierte Auflistungen, z. B. ein verknüpftes Listen-Dictionary, einen Bitvektor sowie Auflistungen, die ausschließlich Zeichenfolgen enthalten.</summary>
    <remarks>
      <format type="text/markdown"><![CDATA[  
  
## Remarks  
 Spezialisierte Sammlungen sind Sammlungen mit sehr spezifischen Zwecken. <xref:System.Collections.Specialized.NameValueCollection>basiert auf <xref:System.Collections.Specialized.NameObjectCollectionBase>, <xref:System.Collections.Specialized.NameValueCollection> akzeptiert jedoch mehrere Werte pro Schlüssel, während <xref:System.Collections.Specialized.NameObjectCollectionBase> nur einen Wert pro Schlüssel akzeptiert.  
  
 Einige stark typisierte Auflistungen im <xref:System.Collections.Specialized> -Namespace sind <xref:System.Collections.Specialized.StringCollection> und <xref:System.Collections.Specialized.StringDictionary>, die beide Werte enthalten, die ausschließlich Zeichen folgen sind.  
  
 Die <xref:System.Collections.Specialized.CollectionsUtil> -Klasse erstellt Instanzen von Auflistungen ohne Berücksichtigung von Groß-und  
  
 Einige Auflistungen transformieren.  Beispielsweise startet die <xref:System.Collections.Specialized.HybridDictionary> <xref:System.Collections.Specialized.ListDictionary> -Klasse als und wird zu einer <xref:System.Collections.Hashtable> , wenn Sie zu groß wird.  <xref:System.Collections.ObjectModel.KeyedCollection%602> Ist eine Liste, erstellt aber auch ein Nachschlage Wörterbuch, wenn die Anzahl der Elemente einen angegebenen Schwellenwert erreicht.  
  
 ]]></format>
    </remarks>
  </Docs>
</Namespace>